hugr_qir/_hugr_qir.pyi
hugr_qir/__init__.py
hugr_qir/cli.py
hugr_qir/.gitignore
hugr_qir/hugr_to_qir.py
hugr_qir/py.typed
hugr_qir/_hugr_qir.abi3.so
hugr_qir/output.py
hugr_qir/.dylibs/libc++abi.1.0.dylib
hugr_qir/.dylibs/libunwind.1.0.dylib
hugr_qir/.dylibs/libc++.1.0.dylib
hugr_qir-0.0.19.dist-info/RECORD
hugr_qir-0.0.19.dist-info/WHEEL
hugr_qir-0.0.19.dist-info/entry_points.txt
hugr_qir-0.0.19.dist-info/METADATA
hugr_qir-0.0.19.dist-info/licenses/LICENSE
