Metadata-Version: 2.4
Name: hugr-qir
Version: 0.0.19
Requires-Dist: click~=8.3.0
Requires-Dist: quantinuum-qircheck~=0.4.0
Requires-Dist: llvmlite~=0.45.1
Requires-Dist: hugr>=0.13.1,<0.15.0
Requires-Dist: guppylang~=0.21.5
License-File: LICENSE
Summary: Quantinuum's tool for converting HUGR to QIR
Requires-Python: >=3.10
